[
  {
    "update": "8244 new cases, 8865 recoveries and 119 deaths in Karnataka\n1334 new cases, 1255 recoveries and 17 deaths in Gujarat\n2488 new cases, 2125 recoveries and 25 deaths in Haryana\n2421 new cases, 1448 recoveries and 67 deaths in Punjab\n306 new cases, 519 recoveries and 13 deaths in Goa\n393 new cases, 457 recoveries and 9 deaths in Puducherry\n96 new cases and 149 recoveries in Manipur\n254 new cases, 130 recoveries and 5 deaths in Chandigarh\n",
    "timestamp": 1600097216
  },
  {
    "update": "13 deaths in Assam\n",
    "timestamp": 1600097992
  },
  {
    "update": "17066 new cases, 15789 recoveries and 363 deaths in Maharashtra\n2403 new cases in Assam\n1730 new cases, 1622 recoveries and 36 deaths in Rajasthan\n",
    "timestamp": 1600101098
  },
  {
    "update": "3211 new cases, 3084 recoveries and 58 deaths in West Bengal\n1918 recoveries in Assam\n3382 recoveries in Odisha\n364 new cases, 68 recoveries and 2 deaths in Himachal Pradesh\n11 new cases, 35 recoveries and 1 death in Andaman and Nicobar Islands\n74 new cases, 39 recoveries and 1 death in Ladakh\n",
    "timestamp": 1600102045
  },
  {
    "update": "1263 new cases, 1529 recoveries and 6 deaths in Jharkhand\n3336 new cases, 1178 recoveries and 18 deaths in Chhattisgarh\n139 new cases, 76 recoveries and 1 death in Meghalaya\n",
    "timestamp": 1600103730
  },
  {
    "update": "2483 new cases, 1713 recoveries and 29 deaths in Madhya Pradesh\n1043 new cases, 1037 recoveries and 15 deaths in Uttarakhand\n3 deaths in Himachal Pradesh\n33 new cases and 16 recoveries in Sikkim\n",
    "timestamp": 1600104431
  },
  {
    "update": "22 recoveries in Rajasthan\n176 new cases, 152 recoveries and 1 death in Arunachal Pradesh\n",
    "timestamp": 1600105663
  },
  {
    "update": "4 new cases in Himachal Pradesh\n1 death in Meghalaya\n89 recoveries in Mizoram\n",
    "timestamp": 1600106439
  },
  {
    "update": "1 death in Goa\n",
    "timestamp": 1600108167
  },
  {
    "update": "2148 new cases, 2180 recoveries and 10 deaths in Telangana\n531 new cases, 389 recoveries and 7 deaths in Tripura\n40 new cases in Mizoram\n",
    "timestamp": 1600140527
  },
  {
    "update": "3645 new cases and 8 deaths in Odisha\n",
    "timestamp": 1600158652
  },
  {
    "update": "5697 new cases, 5735 recoveries and 71 deaths in Tamil Nadu\n",
    "timestamp": 1600175667
  },
  {
    "update": "6841 new cases, 6680 recoveries and 113 deaths in Uttar Pradesh\n1575 new cases, 1514 recoveries and 5 deaths in Bihar\n1329 new cases, 681 recoveries and 19 deaths in Jammu and Kashmir\n15 new cases and 2 deaths in Nagaland\n347 new cases, 202 recoveries and 1 death in Chandigarh\n",
    "timestamp": 1600176568
  },
  {
    "update": "4263 new cases, 3131 recoveries and 36 deaths in Delhi\n375 new cases, 495 recoveries and 11 deaths in Puducherry\n30 recoveries in Nagaland\n8 new cases and 10 recoveries in Dadra and Nagar Haveli and Daman and Diu\n4 recoveries in Mizoram\n",
    "timestamp": 1600177599
  },
  {
    "update": "8846 new cases, 9628 recoveries and 69 deaths in Andhra Pradesh\n613 new cases, 446 recoveries and 11 deaths in Goa\n",
    "timestamp": 1600179363
  },
  {
    "update": "7576 new cases, 7406 recoveries and 97 deaths in Karnataka\n",
    "timestamp": 1600180654
  },
  {
    "update": "1349 new cases, 1444 recoveries and 17 deaths in Gujarat\n2493 new cases, 2454 recoveries and 26 deaths in Haryana\n2382 new cases, 1830 recoveries and 91 deaths in Punjab\n1391 new cases, 1008 recoveries and 9 deaths in Uttarakhand\n9 new cases and 17 recoveries in Dadra and Nagar Haveli and Daman and Diu\n174 new cases, 39 recoveries and 1 death in Meghalaya\n",
    "timestamp": 1600182810
  },
  {
    "update": "3227 new cases, 2919 recoveries and 59 deaths in West Bengal\n2323 new cases, 1902 recoveries and 29 deaths in Madhya Pradesh\n239 new cases, 78 recoveries and 1 death in Manipur\n",
    "timestamp": 1600183633
  },
  {
    "update": "3714 recoveries in Odisha\n",
    "timestamp": 1600184807
  },
  {
    "update": "20432 new cases, 19423 recoveries and 515 deaths in Maharashtra\n2409 new cases and 10 deaths in Assam\n",
    "timestamp": 1600187505
  },
  {
    "update": "1760 new cases, 1711 recoveries and 14 deaths in Rajasthan\n17 new cases, 40 recoveries and 1 death in Andaman and Nicobar Islands\n",
    "timestamp": 1600187869
  },
  {
    "update": "1849 recoveries in Assam\n",
    "timestamp": 1600188406
  },
  {
    "update": "412 new cases, 250 recoveries and 8 deaths in Himachal Pradesh\n",
    "timestamp": 1600189028
  },
  {
    "update": "3215 new cases, 2532 recoveries and 12 deaths in Kerala\n4 new cases in Himachal Pradesh\n",
    "timestamp": 1600190039
  },
  {
    "update": "3450 new cases, 1129 recoveries and 15 deaths in Chhattisgarh\n169 new cases, 127 recoveries and 2 deaths in Arunachal Pradesh\n54 new cases, 169 recoveries and 3 deaths in Sikkim\n",
    "timestamp": 1600190916
  },
  {
    "update": "1702 new cases, 1638 recoveries and 10 deaths in Jharkhand\n1 death in Sikkim\n",
    "timestamp": 1600191976
  },
  {
    "update": "50 new cases in Maharashtra\n",
    "timestamp": 1600193599
  },
  {
    "update": "24 new cases and 21 recoveries in Dadra and Nagar Haveli and Daman and Diu\n",
    "timestamp": 1600195727
  },
  {
    "update": "80 new cases and 42 recoveries in Ladakh\n",
    "timestamp": 1600196360
  },
  {
    "update": "3 deaths in Ladakh\n",
    "timestamp": 1600197118
  },
  {
    "update": "2273 new cases, 2260 recoveries and 12 deaths in Telangana\n12 new cases in Mizoram\n",
    "timestamp": 1600226890
  },
  {
    "update": "4 recoveries in Dadra and Nagar Haveli and Daman and Diu\n",
    "timestamp": 1600234645
  },
  {
    "update": "4270 new cases and 11 deaths in Odisha\n454 new cases, 510 recoveries and 10 deaths in Tripura\n",
    "timestamp": 1600243992
  },
  {
    "update": "8835 new cases, 10845 recoveries and 64 deaths in Andhra Pradesh\n6229 new cases, 6476 recoveries and 86 deaths in Uttar Pradesh\n1531 new cases, 1724 recoveries and 12 deaths in Bihar\n34 new cases and 25 recoveries in Nagaland\n9 new cases and 3 recoveries in Dadra and Nagar Haveli and Daman and Diu\n7 recoveries in Mizoram\n",
    "timestamp": 1600259818
  },
  {
    "update": "3830 new cases, 2263 recoveries and 14 deaths in Kerala\n",
    "timestamp": 1600262761
  },
  {
    "update": "5652 new cases, 5768 recoveries and 57 deaths in Tamil Nadu\n4473 new cases, 3313 recoveries and 33 deaths in Delhi\n2702 new cases, 2756 recoveries and 78 deaths in Punjab\n1590 new cases, 747 recoveries and 18 deaths in Jammu and Kashmir\n510 new cases, 401 recoveries and 13 deaths in Puducherry\n366 new cases, 181 recoveries and 5 deaths in Chandigarh\n14 new cases and 19 recoveries in Dadra and Nagar Haveli and Daman and Diu\n",
    "timestamp": 1600264735
  },
  {
    "update": "1367 new cases, 1447 recoveries and 12 deaths in Gujarat\n",
    "timestamp": 1600268323
  },
  {
    "update": "3237 new cases, 2971 recoveries and 61 deaths in West Bengal\n628 new cases, 351 recoveries and 4 deaths in Goa\n",
    "timestamp": 1600269182
  },
  {
    "update": "9725 new cases, 6580 recoveries and 55 deaths in Karnataka\n4121 recoveries in Odisha\n2462 new cases, 1922 recoveries and 24 deaths in Madhya Pradesh\n1540 new cases, 1192 recoveries and 9 deaths in Uttarakhand\n",
    "timestamp": 1600270642
  },
  {
    "update": "159 new cases and 74 recoveries in Meghalaya\n",
    "timestamp": 1600271206
  },
  {
    "update": "19 deaths in Assam\n2694 new cases, 1771 recoveries and 19 deaths in Haryana\n",
    "timestamp": 1600271871
  },
  {
    "update": "1782 new cases, 1479 recoveries and 15 deaths in Rajasthan\n1635 new cases, 1607 recoveries and 8 deaths in Jharkhand\n",
    "timestamp": 1600273771
  },
  {
    "update": "23365 new cases, 17559 recoveries and 474 deaths in Maharashtra\n2394 new cases in Assam\n19 new cases and 27 recoveries in Andaman and Nicobar Islands\n",
    "timestamp": 1600274320
  },
  {
    "update": "36 new cases, 19 recoveries and 2 deaths in Ladakh\n",
    "timestamp": 1600274802
  },
  {
    "update": "110 new cases, 103 recoveries and 1 death in Manipur\n460 new cases, 114 recoveries and 1 death in Himachal Pradesh\n18 recoveries in Nagaland\n",
    "timestamp": 1600275479
  },
  {
    "update": "3 new cases and 12 recoveries in Dadra and Nagar Haveli and Daman and Diu\n",
    "timestamp": 1600276337
  },
  {
    "update": "2464 recoveries in Assam\n49 new cases and 32 recoveries in Sikkim\n",
    "timestamp": 1600278455
  },
  {
    "update": "3188 new cases, 1646 recoveries and 23 deaths in Chhattisgarh\n226 new cases and 129 recoveries in Arunachal Pradesh\n",
    "timestamp": 1600279079
  },
  {
    "update": "1 new case and 1 recovery in Chhattisgarh\n26 new cases and 10 recoveries in Mizoram\n",
    "timestamp": 1600315999
  },
  {
    "update": "2159 new cases, 2108 recoveries and 9 deaths in Telangana\n527 new cases, 521 recoveries and 5 deaths in Tripura\n",
    "timestamp": 1600316930
  }
]