{
  "DL": {
    "districts": {
      "Delhi": {
        "meta": {
          "population": 19814000
        },
        "total": {
          "confirmed": 3
        }
      }
    },
    "meta": {
      "population": 19814000
    },
    "total": {
      "confirmed": 3
    }
  },
  "GA": {
    "districts": {
      "Unknown": {
        "meta": {
          "tested": {
            "last_updated": "202-10-23"
          }
        },
        "total": {
          "tested": 287887
        }
      }
    },
    "meta": {
      "population": 1540000,
      "tested": {
        "last_updated": "202-10-23"
      }
    },
    "total": {
      "tested": 287887
    }
  },
  "HR": {
    "meta": {
      "population": 28672000,
      "tested": {
        "last_updated": "202-10-23",
        "source": "http://www.nhmharyana.gov.in/WriteReadData/userfiles/file/CoronaVirus/Daily%20Bulletin%20of%20COVID%2019%20as%20on%2023-10-20.pdf"
      }
    },
    "total": {
      "confirmed": 14,
      "tested": 2480029
    }
  },
  "KL": {
    "meta": {
      "population": 35125000
    },
    "total": {
      "confirmed": 3,
      "recovered": 3
    }
  },
  "LA": {
    "delta": {
      "confirmed": 2
    },
    "meta": {
      "population": 293000
    },
    "total": {
      "confirmed": 2
    }
  },
  "RJ": {
    "meta": {
      "population": 77264000
    },
    "total": {
      "confirmed": 2
    }
  },
  "TG": {
    "districts": {
      "Unknown": {
        "total": {
          "confirmed": 1
        }
      }
    },
    "meta": {
      "population": 37220000
    },
    "total": {
      "confirmed": 1
    }
  },
  "TN": {
    "delta": {
      "confirmed": 1
    },
    "meta": {
      "population": 75695000
    },
    "total": {
      "confirmed": 1
    }
  },
  "TT": {
    "delta": {
      "confirmed": 3
    },
    "meta": {
      "population": 1332900000
    },
    "total": {
      "confirmed": 34,
      "recovered": 3
    }
  },
  "UP": {
    "meta": {
      "population": 224979000
    },
    "total": {
      "confirmed": 8
    }
  }
}